UzbekLemmatizer/UzbekLemmatizer.py
UzbekLemmatizer/__init__.py
UzbekLemmatizer/fsms.xml
UzbekLemmatizer/suffixes.xml
uzbeklemmatizer-2.3.dist-info/licenses/LICENSE
uzbeklemmatizer-2.3.dist-info/METADATA
uzbeklemmatizer-2.3.dist-info/WHEEL
uzbeklemmatizer-2.3.dist-info/top_level.txt
uzbeklemmatizer-2.3.dist-info/RECORD
