Metadata-Version: 2.4
Name: UzbekLemmatizer
Version: 2.3
Summary: Uzbek Lemmatizer for Uzbek Language.
Author-email: Sharipov Maksud <maqsbek72@gmail.com>, Yuldashov Ollabergan <ollaberganyuldashov@gmail.com>
License: MIT
Project-URL: Homepage, https://github.com/MaksudSharipov/UzbekLemmatizer
Project-URL: Repository, https://github.com/MaksudSharipov/UzbekLemmatizer
Project-URL: Issues, https://github.com/MaksudSharipov/UzbekLemmatizer/issues
Keywords: uzbek,lemmatizer,nlp
Classifier: Programming Language :: Python :: 3
Classifier: License :: OSI Approved :: MIT License
Classifier: Operating System :: OS Independent
Requires-Python: >=3.7
License-File: LICENSE
Requires-Dist: lxml
Dynamic: license-file
